spirack/B1b_module.py
spirack/B2b_module.py
spirack/D4_module.py
spirack/D4b_module.py
spirack/D5a_module.py
spirack/D5b_module.py
spirack/F1d_module.py
spirack/M2j_module.py
spirack/M2p_module.py
spirack/P2d_module.py
spirack/S4g_module.py
spirack/S5i_module.py
spirack/S5k_module.py
spirack/S5l_module.py
spirack/U1c_module.py
spirack/U2_module.py
spirack/__init__.py
spirack/chip_mode.py
spirack/spi_rack.py
spirack/version.py
spirack-0.2.8.dist-info/LICENSE
spirack-0.2.8.dist-info/METADATA
spirack-0.2.8.dist-info/WHEEL
spirack-0.2.8.dist-info/top_level.txt
spirack-0.2.8.dist-info/RECORD
