Metadata-Version: 2.1
Name: spirack
Version: 0.2.8
Summary: Drivers for the QuTech SPI-rack
Home-page: https://github.com/mtiggelman/SPI-rack
Author: Marijn Tiggelman
Author-email: qutechdev@gmail.com
License: MIT
Keywords: SPI,Qcodes,SPI-rack,QuTech,TU Delft,SPI
Classifier: Programming Language :: Python :: 3
Classifier: License :: OSI Approved :: MIT License
Classifier: Operating System :: OS Independent
License-File: LICENSE
Requires-Dist: pyserial
Requires-Dist: numpy
